putil/__init__.py
putil/compat2.py
putil/compat3.py
putil/eng.py
putil/exdoc.py
putil/exh.py
putil/misc.py
putil/pcontracts.py
putil/pinspect.py
putil/ptypes.py
putil/test.py
putil/tree.py
putil/version.py
putil/pcsv/__init__.py
putil/pcsv/concatenate.py
putil/pcsv/csv_file.py
putil/pcsv/dsort.py
putil/pcsv/merge.py
putil/pcsv/replace.py
putil/pcsv/write.py
putil/plot/__init__.py
putil/plot/basic_source.py
putil/plot/constants.py
putil/plot/csv_source.py
putil/plot/figure.py
putil/plot/functions.py
putil/plot/panel.py
putil/plot/series.py
putil-0.9.12.dist-info/DESCRIPTION.rst
putil-0.9.12.dist-info/METADATA
putil-0.9.12.dist-info/RECORD
putil-0.9.12.dist-info/WHEEL
putil-0.9.12.dist-info/metadata.json
putil-0.9.12.dist-info/top_level.txt
